vtest/__init__.py
vtest/debug.py
vtest/generate.py
vtest/logger.py
vtest/main.py
vtest/plugin.py
vtest/report.py
vtest/tools.py
vtest/vtest.py
vtest-0.1.0.dist-info/entry_points.txt
vtest-0.1.0.dist-info/LICENSE
vtest-0.1.0.dist-info/WHEEL
vtest-0.1.0.dist-info/METADATA
vtest-0.1.0.dist-info/RECORD
